capsul/__init__.py
capsul/__main__.py
capsul/api.py
capsul/info.py
capsul/run.py
capsul/attributes/__init__.py
capsul/attributes/attributes_factory.py
capsul/attributes/attributes_schema.py
capsul/attributes/completion_engine.py
capsul/attributes/completion_engine_factory.py
capsul/attributes/completion_engine_iteration.py
capsul/attributes/fom_completion_engine.py
capsul/attributes/test/__init__.py
capsul/attributes/test/test_attributed_process.py
capsul/attributes/test/test_fom_process.py
capsul/engine/__init__.py
capsul/engine/database.py
capsul/engine/database_json.py
capsul/engine/database_populse.py
capsul/engine/run.py
capsul/engine/settings.py
capsul/engine/write_engine_config.py
capsul/engine/module/__init__.py
capsul/engine/module/afni.py
capsul/engine/module/ants.py
capsul/engine/module/attributes.py
capsul/engine/module/axon.py
capsul/engine/module/fom.py
capsul/engine/module/freesurfer.py
capsul/engine/module/fsl.py
capsul/engine/module/matlab.py
capsul/engine/module/mrtrix.py
capsul/engine/module/nipype.py
capsul/engine/module/python.py
capsul/engine/module/somaworkflow.py
capsul/engine/module/spm.py
capsul/engine/test/__init__.py
capsul/engine/test/test_capsul_engine.py
capsul/in_context/__init__.py
capsul/in_context/afni.py
capsul/in_context/ants.py
capsul/in_context/freesurfer.py
capsul/in_context/fsl.py
capsul/in_context/mrtrix.py
capsul/in_context/nipype.py
capsul/in_context/spm.py
capsul/pipeline/__init__.py
capsul/pipeline/json_io.py
capsul/pipeline/pipeline.py
capsul/pipeline/pipeline_construction.py
capsul/pipeline/pipeline_nodes.py
capsul/pipeline/pipeline_tools.py
capsul/pipeline/pipeline_workflow.py
capsul/pipeline/process_iteration.py
capsul/pipeline/python_export.py
capsul/pipeline/topological_sort.py
capsul/pipeline/xml.py
capsul/pipeline/custom_nodes/__init__.py
capsul/pipeline/custom_nodes/cv_node.py
capsul/pipeline/custom_nodes/loo_node.py
capsul/pipeline/custom_nodes/map_node.py
capsul/pipeline/custom_nodes/reduce_node.py
capsul-2.6.14.dist-info/licenses/LICENSE
capsul-2.6.14.dist-info/METADATA
capsul-2.6.14.dist-info/WHEEL
capsul-2.6.14.dist-info/top_level.txt
capsul-2.6.14.dist-info/RECORD
