Metadata-Version: 2.4
Name: capsul
Version: 2.6.14
Summary: CAPSUL
Home-page: https://github.com/populse/capsul
Author: Populse team
Author-email: support@brainvisa.info
License: CeCILL-B
Platform: OS Independent
Classifier: Development Status :: 5 - Production/Stable
Classifier: Environment :: Console
Classifier: Environment :: X11 Applications :: Qt
Classifier: Operating System :: OS Independent
Classifier: Programming Language :: Python
Classifier: Topic :: Scientific/Engineering
Classifier: Topic :: Utilities
License-File: LICENSE
Requires-Dist: traits>=4.6
Requires-Dist: soma-base>=5.0
Requires-Dist: soma-workflow>=3.2
Requires-Dist: populse-db<4.0,>=3.0
Requires-Dist: six>=1.13
Requires-Dist: PyYAML
Provides-Extra: doc
Requires-Dist: sphinx>=1.0; extra == "doc"
Requires-Dist: numpy>=1.17; extra == "doc"
Provides-Extra: database
Requires-Dist: populse_db; extra == "database"
Provides-Extra: nipype
Requires-Dist: numpy>=1.17; extra == "nipype"
Requires-Dist: scipy>=1.5; extra == "nipype"
Requires-Dist: nibabel>=1.0; extra == "nipype"
Requires-Dist: networkx>=1.0; extra == "nipype"
Requires-Dist: nipype>=1.8; extra == "nipype"
Dynamic: author
Dynamic: author-email
Dynamic: classifier
Dynamic: description
Dynamic: home-page
Dynamic: license
Dynamic: license-file
Dynamic: platform
Dynamic: provides-extra
Dynamic: requires-dist
Dynamic: summary
